liv/__init__.py
liv/ast.py
liv/blocks.py
liv/compat.py
liv/invariant.py
liv/labels.py
liv/liv.py
liv/preprocess.py
liv/programgeneration.py
liv/scope.py
liv/util.py
liv/verifier.py
liv/visualization.py
python_liv-0.1.dev0.dist-info/Apache-2.0.txt
python_liv-0.1.dev0.dist-info/METADATA
python_liv-0.1.dev0.dist-info/WHEEL
python_liv-0.1.dev0.dist-info/top_level.txt
python_liv-0.1.dev0.dist-info/zip-safe
python_liv-0.1.dev0.dist-info/RECORD
